calicam/__init__.py
calicam/__main__.py
calicam/logger.py
calicam/scratch_session_config.py
calicam/session.py
calicam/calibration/charuco.py
calicam/calibration/corner_tracker.py
calicam/calibration/draw_charuco.py
calicam/calibration/monocalibrator.py
calicam/calibration/omnicalibrator.py
calicam/calibration/capture_volume/calibration_diagnostics.py
calicam/calibration/capture_volume/capture_volume.py
calicam/calibration/capture_volume/corner_distance_accuracy.py
calicam/calibration/capture_volume/point_estimates.py
calicam/calibration/capture_volume/helper_functions/get_point_estimates.py
calicam/calibration/capture_volume/helper_functions/get_stereotriangulated_table.py
calicam/cameras/camera.py
calicam/cameras/camera_array.py
calicam/cameras/camera_array_builder.py
calicam/cameras/data_packets.py
calicam/cameras/live_stream.py
calicam/cameras/pyav_sandbox.py
calicam/cameras/synchronizer.py
calicam/gui/main.py
calicam/gui/qt_logger.py
calicam/gui/widgets.py
calicam/gui/wizard_charuco.py
calicam/gui/wizard_directory.py
calicam/gui/camera_config/camera_config_dialogue.py
calicam/gui/camera_config/camera_config_dialogue_old.py
calicam/gui/camera_config/camera_tabs.py
calicam/gui/camera_config/frame_emitter.py
calicam/gui/icons/orb.svg
calicam/gui/icons/rotate-camera-left.svg
calicam/gui/icons/rotate-camera-right.svg
calicam/gui/icons/rotate_right.svg
calicam/gui/omniframe/omni_frame_builder.py
calicam/gui/omniframe/omni_frame_widget.py
calicam/gui/vizualize/camera_mesh.py
calicam/gui/vizualize/capture_volume_dialog.py
calicam/gui/vizualize/capture_volume_visualizer.py
calicam/recording/recorded_stream.py
calicam/recording/undistort_video.py
calicam/recording/video_recorder.py
calicam/triangulate/stereo_points_builder.py
calicam/triangulate/triangulator.py
calicam-0.0.10.dist-info/entry_points.txt
calicam-0.0.10.dist-info/LICENSE.md
calicam-0.0.10.dist-info/WHEEL
calicam-0.0.10.dist-info/METADATA
calicam-0.0.10.dist-info/RECORD
